<annotation>
	<folder>WH_data</folder>
	<filename>2019-11-22_152952.jpg</filename>
	<source>
		<database>WH Data</database>
		<annotation>WH</annotation>
		<image>flickr</image>
		<flickrid>NULL</flickrid>
	</source>
	<owner>
		<flickrid>NULL</flickrid>
		<name>WH</name>
	</owner>
	<size>
		<width>1366</width>
		<height>768</height>
		<depth>3</depth>
	</size>
		<segmented>0</segmented>
	<object>
		<name>people</name>
		<pose>Unspecified</pose>
		<truncated>1</truncated>
		<difficult>0</difficult>
		<bndbox>
			<xmin>668</xmin>
			<ymin>245</ymin>
			<xmax>727</xmax>
			<ymax>419</ymax>
		</bndbox>
	</object>
	<object>
		<name>people</name>
		<pose>Unspecified</pose>
		<truncated>1</truncated>
		<difficult>0</difficult>
		<bndbox>
			<xmin>827</xmin>
			<ymin>206</ymin>
			<xmax>886</xmax>
			<ymax>313</ymax>
		</bndbox>
	</object>
</annotation>