<annotation>
	<folder>tmp</folder>
	<filename>MHDD_3924.jpg</filename>
	<path>D:\us\voc-coal\2863\best\jpg2\MHDD_3924.jpg</path>
	<source>
		<database>Unknown</database>
	</source>
	<size>
		<width>1280</width>
		<height>720</height>
		<depth>3</depth>
	</size>
	<segmented>0</segmented>
	<object>
		<name>helmet</name>
		<pose>Unspecified</pose>
		<truncated>0</truncated>
		<difficult>0</difficult>
		<bndbox>
			<xmin>657</xmin>
			<ymin>90</ymin>
			<xmax>1214</xmax>
			<ymax>520</ymax>
		</bndbox>
	</object>
	<object>
		<name>helmet</name>
		<pose>Unspecified</pose>
		<truncated>0</truncated>
		<difficult>0</difficult>
		<bndbox>
			<xmin>153</xmin>
			<ymin>110</ymin>
			<xmax>543</xmax>
			<ymax>497</ymax>
		</bndbox>
	</object>
</annotation>