<annotation>
	<folder>tmp</folder>
	<filename>MHDD_3665.jpg</filename>
	<path>D:\us\voc-coal\2863\best\jpg2\MHDD_3665.jpg</path>
	<source>
		<database>Unknown</database>
	</source>
	<size>
		<width>882</width>
		<height>886</height>
		<depth>3</depth>
	</size>
	<segmented>0</segmented>
	<object>
		<name>helmet</name>
		<pose>Unspecified</pose>
		<truncated>0</truncated>
		<difficult>0</difficult>
		<bndbox>
			<xmin>113</xmin>
			<ymin>71</ymin>
			<xmax>715</xmax>
			<ymax>833</ymax>
		</bndbox>
	</object>
</annotation>